LICENSE
MANIFEST.in
Makefile
README.md
gvjinja-basic.gv
gvjinja-basic.png
gvjinja.gv
gvjinja.png
gvjinja.py
setup.cfg
setup.py
gvjinja.egg-info/PKG-INFO
gvjinja.egg-info/SOURCES.txt
gvjinja.egg-info/dependency_links.txt
gvjinja.egg-info/not-zip-safe
gvjinja.egg-info/requires.txt
gvjinja.egg-info/top_level.txt