Metadata-Version: 1.1
Name: gvjinja
Version: 0.9b2
Summary: gvjinja - create Graphviz directed graphs for jinja templates
Home-page: https://github.com/vc-h/gvjinja
Author: Victor Hui
Author-email: vc-h@users.noreply.github.com
License: BSD-3-Clause
Download-URL: https://github.com/vc-h/gvjinja/0.9b1tar.gz
Platform: any
Classifier: Topic :: Software Development :: Documentation
Classifier: Topic :: Text Processing :: Markup
Classifier: Environment :: Console
Classifier: Intended Audience :: Developers
Classifier: Operating System :: OS Independent
Classifier: Development Status :: 4 - Beta
Classifier: License :: OSI Approved :: BSD License
Classifier: Programming Language :: Python :: 2.7
Classifier: Programming Language :: Python :: 3.6
